hamamatsu_c11204_01/__init__.py
hamamatsu_c11204_01-1.1.1.dist-info/METADATA
hamamatsu_c11204_01-1.1.1.dist-info/WHEEL
hamamatsu_c11204_01-1.1.1.dist-info/top_level.txt
hamamatsu_c11204_01-1.1.1.dist-info/RECORD
