Metadata-Version: 2.1
Name: hamamatsu-c11204-01
Version: 1.1.1
Summary: Package created to work with a power supply module for MPPC Hamamatsu C11204-01
Home-page: https://gitlab.ahuekna.org.ar/labo_6y7/2024/galan_moreno/software.git
Author: Martín Galan <mng94@live.com.ar>, Cesar Moreno <morenocesar.0098@gmail.com>
License: UNKNOWN
Platform: UNKNOWN
Requires-Python: >=3.6
Requires-Dist: pyserial
